{
  "_class": "group",
  "do_objectID": "5D7B0FA2-611C-420C-8509-E1B634252706",
  "exportOptions": {
    "_class": "exportOptions",
    "exportFormats": [
    ],
    "includedLayerIds": [
    ],
    "layerOptions": 0,
    "shouldTrim": false
  },
  "frame": {
    "_class": "rect",
    "constrainProportions": false,
    "height": 280,
    "width": 936,
    "x": 0,
    "y": 0
  },
  "hasClickThrough": false,
  "isFlippedHorizontal": false,
  "isFlippedVertical": false,
  "isLocked": false,
  "isVisible": true,
  "layerListExpandedType": 1,
  "layers": [
    {
      "class": "shapeGroup",
      "id": "F1096489-C059-490C-96FE-65D5FDC365E6"
    },
    {
      "class": "group",
      "id": "5CD33517-696F-4155-B4F1-A29316787FAD"
    },
    {
      "class": "group",
      "id": "E8C13EB3-0A3C-4678-88B9-DB769DC491CB"
    },
    {
      "class": "group",
      "id": "BA414BC0-5CE7-41D9-9F7D-3EBBD1680FB5"
    }
  ],
  "name": "Scroll-H",
  "nameIsFixed": true,
  "resizingConstraint": 63,
  "resizingType": 0,
  "rotation": 0,
  "shouldBreakMaskChain": false,
  "style": {
    "_class": "style",
    "endDecorationType": 0,
    "miterLimit": 10,
    "startDecorationType": 0
  }
}